google/cloud/sqlalchemy_spanner/__init__.py
google/cloud/sqlalchemy_spanner/_opentelemetry_tracing.py
google/cloud/sqlalchemy_spanner/dml.py
google/cloud/sqlalchemy_spanner/provision.py
google/cloud/sqlalchemy_spanner/requirements.py
google/cloud/sqlalchemy_spanner/sqlalchemy_spanner.py
google/cloud/sqlalchemy_spanner/version.py
sqlalchemy_spanner-1.13.1.dist-info/licenses/LICENSE
sqlalchemy_spanner-1.13.1.dist-info/METADATA
sqlalchemy_spanner-1.13.1.dist-info/WHEEL
sqlalchemy_spanner-1.13.1.dist-info/entry_points.txt
sqlalchemy_spanner-1.13.1.dist-info/top_level.txt
sqlalchemy_spanner-1.13.1.dist-info/RECORD
