Metadata-Version: 2.4
Name: sqlalchemy-spanner
Version: 1.13.1
Summary: SQLAlchemy dialect integrated into Cloud Spanner database
Home-page: https://github.com/cloudspannerecosystem/python-spanner-sqlalchemy
Author: Google LLC
Author-email: googleapis-packages@google.com
Classifier: Intended Audience :: Developers
License-File: LICENSE
Requires-Dist: sqlalchemy>=1.1.13
Requires-Dist: google-cloud-spanner>=3.55.0
Requires-Dist: alembic
Provides-Extra: tracing
Requires-Dist: opentelemetry-api>=1.1.0; extra == "tracing"
Requires-Dist: opentelemetry-sdk>=1.1.0; extra == "tracing"
Requires-Dist: opentelemetry-instrumentation>=0.20b0; extra == "tracing"
Dynamic: author
Dynamic: author-email
Dynamic: classifier
Dynamic: description
Dynamic: home-page
Dynamic: license-file
Dynamic: provides-extra
Dynamic: requires-dist
Dynamic: summary
